{"cameraMode":{"drawMode":0,"name":"Shaded","section":"Shading Mode"},"sceneLighting":true,"audioPlay":false,"sceneViewState":{"showFog":true,"showMaterialUpdate":false,"showSkybox":true,"showFlares":true,"showImageEffects":true,"showParticleSystems":true,"showVisualEffectGraphs":true,"m_FxEnabled":true},"in2DMode":false,"pivot":{"x":-5.46306037902832,"y":-3.674541473388672,"z":-0.750228762626648},"rotation":{"x":-0.20084190368652345,"y":0.6655364036560059,"z":-0.19304469227790833,"w":-0.6924317479133606},"size":12.152617454528809,"orthographic":false}